<?xml version="1.0" encoding="utf-8"?>
<items>
<item><title>Kevin Bacon</title><url>https://en.wikipedia.org/wiki/Kevin_Bacon</url><lastUpdated> This page was last edited on 9 December 2022, at 04:16</lastUpdated></item>
<item><title> (TV series)</title><url>https://en.wikipedia.org/wiki/I_Love_Dick_(TV_series)</url><lastUpdated> This page was last edited on 14 November 2022, at 23:25</lastUpdated></item>
<item><title>Primetime Emmy Awards</title><url>https://en.wikipedia.org/wiki/Primetime_Emmy_Award</url><lastUpdated> This page was last edited on 24 November 2022, at 19:45</lastUpdated></item>
<item><title>Screen Actors Guild Awards</title><url>https://en.wikipedia.org/wiki/Screen_Actors_Guild_Award</url><lastUpdated> This page was last edited on 4 December 2022, at 15:58</lastUpdated></item>
<item><title>Golden Globe Award for Best Actor – Television Series Musical or Comedy</title><url>https://en.wikipedia.org/wiki/Golden_Globe_Award_for_Best_Actor_%E2%80%93_Television_Series_Musical_or_Comedy</url><lastUpdated> This page was last edited on 13 December 2022, at 15:12</lastUpdated></item>
<item><title>SixDegrees.org</title><url>https://en.wikipedia.org/wiki/SixDegrees.org</url><lastUpdated> This page was last edited on 2 March 2021, at 15:35</lastUpdated></item>
<item><title>Six Degrees of Kevin Bacon</title><url>https://en.wikipedia.org/wiki/Six_Degrees_of_Kevin_Bacon</url><lastUpdated> This page was last edited on 9 November 2022, at 21:52</lastUpdated></item>
<item><title>EE Limited</title><url>https://en.wikipedia.org/wiki/EE_Limited</url><lastUpdated> This page was last edited on 11 December 2022, at 21:04</lastUpdated></item>
<item><title>Hollywood Walk of Fame</title><url>https://en.wikipedia.org/wiki/Hollywood_Walk_of_Fame</url><lastUpdated> This page was last edited on 4 December 2022, at 17:18</lastUpdated></item>
<item><title>Golden Globe Awards</title><url>https://en.wikipedia.org/wiki/Golden_Globe_Award</url><lastUpdated> This page was last edited on 13 December 2022, at 14:57</lastUpdated></item>
<item><title>None</title><url>https://en.wikipedia.org/wiki/Taking_Chance</url><lastUpdated> This page was last edited on 30 November 2022, at 18:50</lastUpdated></item>
<item><title>None</title><url>https://en.wikipedia.org/wiki/The_Guardian</url><lastUpdated> This page was last edited on 23 November 2022, at 16:39</lastUpdated></item>
<item><title>None</title><url>https://en.wikipedia.org/wiki/The_Following</url><lastUpdated> This page was last edited on 28 November 2022, at 23:08</lastUpdated></item>
<item><title>Academy Awards</title><url>https://en.wikipedia.org/wiki/Academy_Award</url><lastUpdated> This page was last edited on 8 December 2022, at 20:25</lastUpdated></item>
<item><title>Joel Schumacher</title><url>https://en.wikipedia.org/wiki/Joel_Schumacher</url><lastUpdated> This page was last edited on 14 November 2022, at 14:33</lastUpdated></item>
<item><title>Fox Broadcasting Company</title><url>https://en.wikipedia.org/wiki/Fox_Broadcasting_Company</url><lastUpdated> This page was last edited on 29 November 2022, at 02:15</lastUpdated></item>
<item><title>None</title><url>https://en.wikipedia.org/wiki/Access_Hollywood</url><lastUpdated> This page was last edited on 11 December 2022, at 06:33</lastUpdated></item>
<item><title>Main Page</title><url>https://en.wikipedia.org/wiki/Main_Page</url><lastUpdated> This page was last edited on 5 October 2022, at 19:27</lastUpdated></item>
<item><title>HBO</title><url>https://en.wikipedia.org/wiki/HBO</url><lastUpdated> This page was last edited on 9 December 2022, at 11:04</lastUpdated></item>
</items>